Metadata-Version: 2.4
Name: llama-index-llms-qianfan
Version: 0.4.1
Summary: llama-index llms baidu qianfan integration
Author-email: wencan <wencan@live.cn>
License-Expression: MIT
License-File: LICENSE
Requires-Python: <4.0,>=3.9
Requires-Dist: llama-index-core<0.15,>=0.13.0
Requires-Dist: llama-index-utils-qianfan<0.5,>=0.4.0
